README.txt
setup.py
utiltest/__init__.py
utiltest/util_test.py
utiltest.egg-info/PKG-INFO
utiltest.egg-info/SOURCES.txt
utiltest.egg-info/dependency_links.txt
utiltest.egg-info/top_level.txt
utiltest.egg-info/zip-safe