Metadata-Version: 1.1
Name: utiltest
Version: 1.0.1
Summary: this is a test package for packing python liberaries tutorial.
Home-page: http://blog.csdn.net/u011672579
Author: Daiwei
Author-email: 629569794@qq.com
License: MIT
Keywords: test python package
Platform: UNKNOWN
Classifier: License :: OSI Approved :: MIT License
Classifier: Programming Language :: Python
Classifier: Intended Audience :: Developers
Classifier: Operating System :: OS Independent
